datasketches.so
src/__init__.py
tests/__init__.py
tests/cpc_test.py
tests/fi_test.py
tests/hll_test.py
tests/kll_test.py
tests/theta_test.py
tests/vector_of_kll_test.py
tests/vo_test.py
whylabs_datasketches-2.2.0b1.dist-info/LICENSE
whylabs_datasketches-2.2.0b1.dist-info/METADATA
whylabs_datasketches-2.2.0b1.dist-info/NOTICE
whylabs_datasketches-2.2.0b1.dist-info/WHEEL
whylabs_datasketches-2.2.0b1.dist-info/top_level.txt
whylabs_datasketches-2.2.0b1.dist-info/RECORD
