Metadata-Version: 2.1
Name: whylabs-datasketches
Version: 2.2.0b1
Summary: A wrapper for the C++ Datasketches library
Home-page: http://datasketches.apache.org
Author: Datasketches Developers
Author-email: dev@datasketches.apache.org
License: Apache License 2.0
Platform: UNKNOWN
